[{"domain":"one.download","status":"available","attractiveness":132,"demand":44,"length":3,"created":"","expires":"","registrar":null,"sectors":"Business,General,Media,Technology"},{"domain":"second.download","status":"available","attractiveness":120,"demand":23,"length":6,"created":"","expires":"","registrar":null,"sectors":"General,Mathematics"},{"domain":"flat.download","status":"available","attractiveness":116,"demand":24,"length":4,"created":"","expires":"","registrar":null,"sectors":"Construction,Real Estate"},{"domain":"tenth.download","status":"available","attractiveness":116,"demand":7,"length":5,"created":"","expires":"","registrar":null,"sectors":"Mathematics"},{"domain":"zero.download","status":"available","attractiveness":112,"demand":49,"length":4,"created":"","expires":"","registrar":null,"sectors":"Mathematics"},{"domain":"eight.download","status":"available","attractiveness":102,"demand":23,"length":5,"created":"","expires":"","registrar":null,"sectors":"General,Mathematics"},{"domain":"third.download","status":"available","attractiveness":100,"demand":16,"length":5,"created":"","expires":"","registrar":null,"sectors":"Mathematics"},{"domain":"crack.download","status":"available","attractiveness":100,"demand":20,"length":5,"created":"","expires":"","registrar":null,"sectors":"Sports"},{"domain":"sixth.download","status":"available","attractiveness":100,"demand":8,"length":5,"created":"","expires":"","registrar":null,"sectors":"Mathematics"},{"domain":"ninth.download","status":"available","attractiveness":100,"demand":9,"length":5,"created":"","expires":"","registrar":null,"sectors":"Mathematics"},{"domain":"eighth.download","status":"available","attractiveness":100,"demand":6,"length":6,"created":"","expires":"","registrar":null,"sectors":"Mathematics"},{"domain":"nought.download","status":"available","attractiveness":92,"demand":4,"length":6,"created":"","expires":"","registrar":null,"sectors":"Mathematics"},{"domain":"twentieth.download","status":"available","attractiveness":92,"demand":3,"length":9,"created":"","expires":"","registrar":null,"sectors":"Mathematics"},{"domain":"leash.download","status":"available","attractiveness":90,"demand":7,"length":5,"created":"","expires":"","registrar":null,"sectors":"General,Health and Fitness,Retail"},{"domain":"three.download","status":"available","attractiveness":88,"demand":24,"length":5,"created":"","expires":"","registrar":null,"sectors":"Mathematics"},{"domain":"ace.download","status":"available","attractiveness":88,"demand":34,"length":3,"created":"","expires":"","registrar":null,"sectors":"Sports"},{"domain":"twelve.download","status":"available","attractiveness":88,"demand":18,"length":6,"created":"","expires":"","registrar":null,"sectors":"General,Mathematics"},{"domain":"hundred.download","status":"available","attractiveness":88,"demand":14,"length":7,"created":"","expires":"","registrar":null,"sectors":"Mathematics"},{"domain":"sixteen.download","status":"available","attractiveness":88,"demand":11,"length":7,"created":"","expires":"","registrar":null,"sectors":"Mathematics"},{"domain":"fifteen.download","status":"available","attractiveness":88,"demand":13,"length":7,"created":"","expires":"","registrar":null,"sectors":"Mathematics"},{"domain":"eleven.download","status":"available","attractiveness":88,"demand":33,"length":6,"created":"","expires":"","registrar":null,"sectors":"Mathematics"},{"domain":"ten.download","status":"available","attractiveness":88,"demand":28,"length":3,"created":"","expires":"","registrar":null,"sectors":"General,Mathematics"},{"domain":"xiv.download","status":"available","attractiveness":86,"demand":12,"length":3,"created":"","expires":"","registrar":null,"sectors":"Mathematics"},{"domain":"xix.download","status":"available","attractiveness":86,"demand":11,"length":3,"created":"","expires":"","registrar":null,"sectors":"Mathematics"},{"domain":"cipher.download","status":"available","attractiveness":86,"demand":29,"length":6,"created":"","expires":"","registrar":null,"sectors":"Mathematics"},{"domain":"fourteen.download","status":"available","attractiveness":84,"demand":8,"length":8,"created":"","expires":"","registrar":null,"sectors":"Mathematics"},{"domain":"thousand.download","status":"available","attractiveness":84,"demand":8,"length":8,"created":"","expires":"","registrar":null,"sectors":"Mathematics"},{"domain":"seventeen.download","status":"available","attractiveness":84,"demand":7,"length":9,"created":"","expires":"","registrar":null,"sectors":"Mathematics"},{"domain":"grand.download","status":"available","attractiveness":84,"demand":25,"length":5,"created":"","expires":"","registrar":null,"sectors":"Finance,General"},{"domain":"thirteen.download","status":"available","attractiveness":84,"demand":10,"length":8,"created":"","expires":"","registrar":null,"sectors":"Mathematics"},{"domain":"twentytwo.download","status":"available","attractiveness":84,"demand":11,"length":10,"created":"","expires":"","registrar":null,"sectors":"Mathematics"},{"domain":"nineteen.download","status":"available","attractiveness":84,"demand":8,"length":8,"created":"","expires":"","registrar":null,"sectors":"Mathematics"},{"domain":"twentyone.download","status":"available","attractiveness":84,"demand":13,"length":10,"created":"","expires":"","registrar":null,"sectors":"Mathematics"},{"domain":"fivesome.download","status":"available","attractiveness":82,"demand":1,"length":8,"created":"","expires":"","registrar":null,"sectors":"Sports"},{"domain":"decade.download","status":"available","attractiveness":82,"demand":10,"length":6,"created":"","expires":"","registrar":null,"sectors":"Mathematics"},{"domain":"dozen.download","status":"available","attractiveness":82,"demand":10,"length":5,"created":"","expires":"","registrar":null,"sectors":"Mathematics"},{"domain":"first.download","status":"available","attractiveness":80,"demand":36,"length":5,"created":"","expires":"","registrar":null,"sectors":"General,Mathematics"},{"domain":"seventh.download","status":"available","attractiveness":80,"demand":10,"length":7,"created":"","expires":"","registrar":null,"sectors":"Mathematics"},{"domain":"two.download","status":"available","attractiveness":80,"demand":24,"length":3,"created":"","expires":"","registrar":null,"sectors":"Mathematics"},{"domain":"trio.download","status":"available","attractiveness":80,"demand":21,"length":4,"created":"","expires":"","registrar":null,"sectors":"Entertainment"},{"domain":"forty.download","status":"available","attractiveness":80,"demand":9,"length":5,"created":"","expires":"","registrar":null,"sectors":"Mathematics"},{"domain":"nine.download","status":"available","attractiveness":80,"demand":24,"length":4,"created":"","expires":"","registrar":null,"sectors":"General,Mathematics"},{"domain":"yard.download","status":"available","attractiveness":80,"demand":26,"length":4,"created":"","expires":"","registrar":null,"sectors":"Construction,General"},{"domain":"twenty.download","status":"available","attractiveness":80,"demand":12,"length":6,"created":"","expires":"","registrar":null,"sectors":"Mathematics"},{"domain":"sixtynine.download","status":"available","attractiveness":78,"demand":8,"length":10,"created":"","expires":"","registrar":null,"sectors":"Mathematics"},{"domain":"twentysix.download","status":"available","attractiveness":78,"demand":8,"length":10,"created":"","expires":"","registrar":null,"sectors":"Mathematics"},{"domain":"nineteenth.download","status":"available","attractiveness":76,"demand":3,"length":10,"created":"","expires":"","registrar":null,"sectors":"Mathematics"},{"domain":"fourteenth.download","status":"available","attractiveness":76,"demand":1,"length":10,"created":"","expires":"","registrar":null,"sectors":"Mathematics"},{"domain":"hundredth.download","status":"available","attractiveness":76,"demand":1,"length":9,"created":"","expires":"","registrar":null,"sectors":"Mathematics"},{"domain":"thirteenth.download","status":"available","attractiveness":76,"demand":4,"length":10,"created":"","expires":"","registrar":null,"sectors":"Mathematics"},{"domain":"threed.download","status":"available","attractiveness":76,"demand":7,"length":7,"created":"","expires":"","registrar":null,"sectors":"Technology"},{"domain":"fifteenth.download","status":"available","attractiveness":76,"demand":2,"length":9,"created":"","expires":"","registrar":null,"sectors":"Mathematics"},{"domain":"thousandth.download","status":"available","attractiveness":76,"demand":1,"length":10,"created":"","expires":"","registrar":null,"sectors":"Mathematics"},{"domain":"firstrate.download","status":"available","attractiveness":76,"demand":6,"length":10,"created":"","expires":"","registrar":null,"sectors":"Business"},{"domain":"eighteen.download","status":"available","attractiveness":76,"demand":7,"length":8,"created":"","expires":"","registrar":null,"sectors":"Mathematics"},{"domain":"single.download","status":"available","attractiveness":74,"demand":19,"length":6,"created":"","expires":"","registrar":null,"sectors":"Sports"},{"domain":"sixtieth.download","status":"available","attractiveness":72,"demand":1,"length":8,"created":"","expires":"","registrar":null,"sectors":"Mathematics"},{"domain":"eightieth.download","status":"available","attractiveness":72,"demand":1,"length":9,"created":"","expires":"","registrar":null,"sectors":"Mathematics"},{"domain":"trey.download","status":"available","attractiveness":72,"demand":14,"length":4,"created":"","expires":"","registrar":null,"sectors":"Sports"},{"domain":"ternary.download","status":"available","attractiveness":72,"demand":7,"length":7,"created":"","expires":"","registrar":null,"sectors":"Mathematics"},{"domain":"trinity.download","status":"available","attractiveness":72,"demand":18,"length":7,"created":"","expires":"","registrar":null,"sectors":"Religion"},{"domain":"seventieth.download","status":"available","attractiveness":72,"demand":1,"length":10,"created":"","expires":"","registrar":null,"sectors":"Mathematics"},{"domain":"liv.download","status":"available","attractiveness":72,"demand":27,"length":3,"created":"","expires":"","registrar":null,"sectors":"Mathematics"},{"domain":"ninetieth.download","status":"available","attractiveness":72,"demand":1,"length":9,"created":"","expires":"","registrar":null,"sectors":"Mathematics"},{"domain":"unity.download","status":"available","attractiveness":70,"demand":40,"length":5,"created":"","expires":"","registrar":null,"sectors":"Mathematics"},{"domain":"tiptop.download","status":"available","attractiveness":70,"demand":24,"length":6,"created":"","expires":"","registrar":null,"sectors":"Fashion"},{"domain":"fiftieth.download","status":"available","attractiveness":68,"demand":0,"length":8,"created":"","expires":"","registrar":null,"sectors":"Mathematics"},{"domain":"threesome.download","status":"available","attractiveness":68,"demand":5,"length":9,"created":"","expires":"","registrar":null,"sectors":"Entertainment"},{"domain":"foursome.download","status":"available","attractiveness":68,"demand":4,"length":8,"created":"","expires":"","registrar":null,"sectors":"Sports"},{"domain":"ane.download","status":"available","attractiveness":68,"demand":12,"length":3,"created":"","expires":"","registrar":null,"sectors":"Mathematics"},{"domain":"ennead.download","status":"available","attractiveness":68,"demand":5,"length":6,"created":"","expires":"","registrar":null,"sectors":"Mathematics"},{"domain":"octonary.download","status":"available","attractiveness":68,"demand":1,"length":8,"created":"","expires":"","registrar":null,"sectors":"Mathematics"},{"domain":"sevener.download","status":"available","attractiveness":68,"demand":1,"length":7,"created":"","expires":"","registrar":null,"sectors":"Mathematics"},{"domain":"thirtieth.download","status":"available","attractiveness":68,"demand":1,"length":9,"created":"","expires":"","registrar":null,"sectors":"Mathematics"},{"domain":"fortieth.download","status":"available","attractiveness":68,"demand":0,"length":8,"created":"","expires":"","registrar":null,"sectors":"Mathematics"},{"domain":"septenary.download","status":"available","attractiveness":68,"demand":1,"length":9,"created":"","expires":"","registrar":null,"sectors":"Mathematics"},{"domain":"fifty.download","status":"available","attractiveness":66,"demand":12,"length":5,"created":"","expires":"","registrar":null,"sectors":"Mathematics"},{"domain":"century.download","status":"available","attractiveness":66,"demand":17,"length":7,"created":"","expires":"","registrar":null,"sectors":"Education"},{"domain":"xxii.download","status":"available","attractiveness":66,"demand":6,"length":4,"created":"","expires":"","registrar":null,"sectors":"Mathematics"},{"domain":"sextet.download","status":"available","attractiveness":66,"demand":1,"length":6,"created":"","expires":"","registrar":null,"sectors":"Entertainment"},{"domain":"thirty.download","status":"available","attractiveness":66,"demand":8,"length":6,"created":"","expires":"","registrar":null,"sectors":"Mathematics"},{"domain":"acappella.download","status":"available","attractiveness":66,"demand":6,"length":10,"created":"","expires":"","registrar":null,"sectors":"Entertainment"},{"domain":"tenner.download","status":"available","attractiveness":66,"demand":5,"length":6,"created":"","expires":"","registrar":null,"sectors":"Finance"},{"domain":"six.download","status":"available","attractiveness":66,"demand":26,"length":3,"created":"","expires":"","registrar":null,"sectors":"Mathematics"},{"domain":"eighty.download","status":"available","attractiveness":66,"demand":6,"length":6,"created":"","expires":"","registrar":null,"sectors":"Mathematics"},{"domain":"latest.download","status":"available","attractiveness":66,"demand":18,"length":6,"created":"","expires":"","registrar":null,"sectors":"Technology"},{"domain":"five.download","status":"available","attractiveness":66,"demand":26,"length":4,"created":"","expires":"","registrar":null,"sectors":"Mathematics"},{"domain":"xii.download","status":"available","attractiveness":66,"demand":10,"length":3,"created":"","expires":"","registrar":null,"sectors":"Mathematics"},{"domain":"ninety.download","status":"available","attractiveness":66,"demand":11,"length":6,"created":"","expires":"","registrar":null,"sectors":"Mathematics"},{"domain":"xxv.download","status":"available","attractiveness":66,"demand":6,"length":3,"created":"","expires":"","registrar":null,"sectors":"Mathematics"},{"domain":"xiii.download","status":"available","attractiveness":66,"demand":9,"length":4,"created":"","expires":"","registrar":null,"sectors":"Mathematics"},{"domain":"xxvi.download","status":"available","attractiveness":66,"demand":3,"length":4,"created":"","expires":"","registrar":null,"sectors":"Mathematics"},{"domain":"xvii.download","status":"available","attractiveness":66,"demand":5,"length":4,"created":"","expires":"","registrar":null,"sectors":"Mathematics"},{"domain":"deuce.download","status":"available","attractiveness":66,"demand":9,"length":5,"created":"","expires":"","registrar":null,"sectors":"Sports"},{"domain":"four.download","status":"available","attractiveness":66,"demand":27,"length":4,"created":"","expires":"","registrar":null,"sectors":"Mathematics"},{"domain":"xvi.download","status":"available","attractiveness":66,"demand":5,"length":3,"created":"","expires":"","registrar":null,"sectors":"Mathematics"},{"domain":"onec.download","status":"available","attractiveness":66,"demand":6,"length":5,"created":"","expires":"","registrar":null,"sectors":"Mathematics"},{"domain":"xxi.download","status":"available","attractiveness":66,"demand":10,"length":3,"created":"","expires":"","registrar":null,"sectors":"Mathematics"},{"domain":"clv.download","status":"available","attractiveness":66,"demand":10,"length":3,"created":"","expires":"","registrar":null,"sectors":"Mathematics"},{"domain":"xviii.download","status":"available","attractiveness":66,"demand":5,"length":5,"created":"","expires":"","registrar":null,"sectors":"Mathematics"},{"domain":"eleventh.download","status":"available","attractiveness":62,"demand":5,"length":8,"created":"","expires":"","registrar":null,"sectors":"Mathematics"},{"domain":"longdozen.download","status":"available","attractiveness":62,"demand":2,"length":10,"created":"","expires":"","registrar":null,"sectors":"Mathematics"},{"domain":"twodozen.download","status":"available","attractiveness":62,"demand":1,"length":9,"created":"","expires":"","registrar":null,"sectors":"Mathematics"},{"domain":"sixteenth.download","status":"available","attractiveness":62,"demand":1,"length":9,"created":"","expires":"","registrar":null,"sectors":"Mathematics"},{"domain":"troika.download","status":"available","attractiveness":62,"demand":8,"length":6,"created":"","expires":"","registrar":null,"sectors":"Politics"},{"domain":"eighteenth.download","status":"available","attractiveness":62,"demand":1,"length":10,"created":"","expires":"","registrar":null,"sectors":"Mathematics"},{"domain":"fortyfour.download","status":"available","attractiveness":62,"demand":6,"length":10,"created":"","expires":"","registrar":null,"sectors":"Mathematics"},{"domain":"quartet.download","status":"available","attractiveness":62,"demand":7,"length":7,"created":"","expires":"","registrar":null,"sectors":"Arts,Entertainment"},{"domain":"chiliad.download","status":"available","attractiveness":62,"demand":2,"length":7,"created":"","expires":"","registrar":null,"sectors":"Mathematics"},{"domain":"cxv.download","status":"available","attractiveness":60,"demand":4,"length":3,"created":"","expires":"","registrar":null,"sectors":"Mathematics"},{"domain":"cxxx.download","status":"available","attractiveness":60,"demand":4,"length":4,"created":"","expires":"","registrar":null,"sectors":"Mathematics"},{"domain":"clxxx.download","status":"available","attractiveness":60,"demand":1,"length":5,"created":"","expires":"","registrar":null,"sectors":"Mathematics"},{"domain":"tertiary.download","status":"available","attractiveness":60,"demand":4,"length":8,"created":"","expires":"","registrar":null,"sectors":"Education"},{"domain":"xcl.download","status":"available","attractiveness":60,"demand":5,"length":3,"created":"","expires":"","registrar":null,"sectors":"Mathematics"},{"domain":"eightysix.download","status":"available","attractiveness":60,"demand":7,"length":10,"created":"","expires":"","registrar":null,"sectors":"Mathematics"},{"domain":"cxlv.download","status":"available","attractiveness":60,"demand":2,"length":4,"created":"","expires":"","registrar":null,"sectors":"Mathematics"},{"domain":"clxx.download","status":"available","attractiveness":60,"demand":3,"length":4,"created":"","expires":"","registrar":null,"sectors":"Mathematics"},{"domain":"thou.download","status":"available","attractiveness":60,"demand":7,"length":4,"created":"","expires":"","registrar":null,"sectors":"Mathematics"},{"domain":"cxxv.download","status":"available","attractiveness":60,"demand":1,"length":4,"created":"","expires":"","registrar":null,"sectors":"Mathematics"},{"domain":"clx.download","status":"available","attractiveness":60,"demand":10,"length":3,"created":"","expires":"","registrar":null,"sectors":"Mathematics"},{"domain":"clxxv.download","status":"available","attractiveness":60,"demand":1,"length":5,"created":"","expires":"","registrar":null,"sectors":"Mathematics"},{"domain":"cxx.download","status":"available","attractiveness":60,"demand":10,"length":3,"created":"","expires":"","registrar":null,"sectors":"Mathematics"},{"domain":"clxv.download","status":"available","attractiveness":60,"demand":1,"length":4,"created":"","expires":"","registrar":null,"sectors":"Mathematics"},{"domain":"cxl.download","status":"available","attractiveness":60,"demand":7,"length":3,"created":"","expires":"","registrar":null,"sectors":"Mathematics"},{"domain":"cxxxv.download","status":"available","attractiveness":60,"demand":2,"length":5,"created":"","expires":"","registrar":null,"sectors":"Mathematics"},{"domain":"sixty.download","status":"available","attractiveness":60,"demand":13,"length":5,"created":"","expires":"","registrar":null,"sectors":"Mathematics"},{"domain":"fifth.download","status":"available","attractiveness":58,"demand":12,"length":5,"created":"","expires":"","registrar":null,"sectors":"Mathematics"},{"domain":"twelfth.download","status":"available","attractiveness":58,"demand":2,"length":7,"created":"","expires":"","registrar":null,"sectors":"Mathematics"},{"domain":"alacarte.download","status":"available","attractiveness":58,"demand":11,"length":10,"created":"","expires":"","registrar":null,"sectors":"Food and Beverage"},{"domain":"lxxx.download","status":"available","attractiveness":58,"demand":2,"length":4,"created":"","expires":"","registrar":null,"sectors":"Mathematics"},{"domain":"hexad.download","status":"available","attractiveness":58,"demand":4,"length":5,"created":"","expires":"","registrar":null,"sectors":"Mathematics"},{"domain":"seventy.download","status":"available","attractiveness":58,"demand":7,"length":7,"created":"","expires":"","registrar":null,"sectors":"Mathematics"},{"domain":"sixer.download","status":"available","attractiveness":58,"demand":5,"length":5,"created":"","expires":"","registrar":null,"sectors":"Sports"},{"domain":"centesimal.download","status":"available","attractiveness":58,"demand":1,"length":10,"created":"","expires":"","registrar":null,"sectors":"Mathematics"},{"domain":"pentad.download","status":"available","attractiveness":58,"demand":2,"length":6,"created":"","expires":"","registrar":null,"sectors":"Mathematics"},{"domain":"sixtyone.download","status":"available","attractiveness":58,"demand":3,"length":9,"created":"","expires":"","registrar":null,"sectors":"Mathematics"},{"domain":"seven.download","status":"available","attractiveness":58,"demand":36,"length":5,"created":"","expires":"","registrar":null,"sectors":"Mathematics"},{"domain":"sextuplet.download","status":"available","attractiveness":58,"demand":1,"length":9,"created":"","expires":"","registrar":null,"sectors":"Healthcare"},{"domain":"eighter.download","status":"available","attractiveness":58,"demand":2,"length":7,"created":"","expires":"","registrar":null,"sectors":"Mathematics"},{"domain":"octad.download","status":"available","attractiveness":58,"demand":5,"length":5,"created":"","expires":"","registrar":null,"sectors":"Mathematics"},{"domain":"tetrad.download","status":"available","attractiveness":58,"demand":5,"length":6,"created":"","expires":"","registrar":null,"sectors":"Mathematics"},{"domain":"niner.download","status":"available","attractiveness":58,"demand":5,"length":5,"created":"","expires":"","registrar":null,"sectors":"Mathematics"},{"domain":"fourscore.download","status":"available","attractiveness":58,"demand":4,"length":9,"created":"","expires":"","registrar":null,"sectors":"Mathematics"},{"domain":"super.download","status":"resell","attractiveness":58,"demand":47,"length":5,"created":"2016-09-05T19:28:38.000Z","expires":"2026-09-04T23:59:59.000Z","registrar":"1API GmbH","sectors":"Business"},{"domain":"heptad.download","status":"available","attractiveness":58,"demand":1,"length":6,"created":"","expires":"","registrar":null,"sectors":"Mathematics"},{"domain":"xxxvii.download","status":"available","attractiveness":56,"demand":2,"length":6,"created":"","expires":"","registrar":null,"sectors":"Mathematics"},{"domain":"xxiii.download","status":"available","attractiveness":56,"demand":5,"length":5,"created":"","expires":"","registrar":null,"sectors":"Mathematics"},{"domain":"xxxviii.download","status":"available","attractiveness":56,"demand":1,"length":7,"created":"","expires":"","registrar":null,"sectors":"Mathematics"},{"domain":"xliv.download","status":"available","attractiveness":56,"demand":2,"length":4,"created":"","expires":"","registrar":null,"sectors":"Mathematics"},{"domain":"fortytwo.download","status":"available","attractiveness":56,"demand":17,"length":9,"created":"","expires":"","registrar":null,"sectors":"Mathematics"},{"domain":"xxxiii.download","status":"available","attractiveness":56,"demand":2,"length":6,"created":"","expires":"","registrar":null,"sectors":"Mathematics"},{"domain":"xlii.download","status":"available","attractiveness":56,"demand":5,"length":4,"created":"","expires":"","registrar":null,"sectors":"Mathematics"},{"domain":"xxxi.download","status":"available","attractiveness":56,"demand":9,"length":4,"created":"","expires":"","registrar":null,"sectors":"Mathematics"},{"domain":"lviii.download","status":"available","attractiveness":56,"demand":1,"length":5,"created":"","expires":"","registrar":null,"sectors":"Mathematics"},{"domain":"fortynine.download","status":"available","attractiveness":56,"demand":3,"length":10,"created":"","expires":"","registrar":null,"sectors":"Mathematics"},{"domain":"fiftynine.download","status":"available","attractiveness":56,"demand":4,"length":10,"created":"","expires":"","registrar":null,"sectors":"Mathematics"},{"domain":"lvii.download","status":"available","attractiveness":56,"demand":1,"length":4,"created":"","expires":"","registrar":null,"sectors":"Mathematics"},{"domain":"fortysix.download","status":"available","attractiveness":56,"demand":3,"length":9,"created":"","expires":"","registrar":null,"sectors":"Mathematics"},{"domain":"ilx.download","status":"available","attractiveness":56,"demand":5,"length":3,"created":"","expires":"","registrar":null,"sectors":"Mathematics"},{"domain":"xxxvi.download","status":"available","attractiveness":56,"demand":1,"length":5,"created":"","expires":"","registrar":null,"sectors":"Mathematics"},{"domain":"xlvii.download","status":"available","attractiveness":56,"demand":2,"length":5,"created":"","expires":"","registrar":null,"sectors":"Mathematics"},{"domain":"fiftytwo.download","status":"available","attractiveness":56,"demand":6,"length":9,"created":"","expires":"","registrar":null,"sectors":"Mathematics"},{"domain":"xxix.download","status":"available","attractiveness":56,"demand":4,"length":4,"created":"","expires":"","registrar":null,"sectors":"Mathematics"},{"domain":"fiftyfour.download","status":"available","attractiveness":56,"demand":3,"length":10,"created":"","expires":"","registrar":null,"sectors":"Mathematics"},{"domain":"fortyone.download","status":"available","attractiveness":56,"demand":4,"length":9,"created":"","expires":"","registrar":null,"sectors":"Mathematics"},{"domain":"lii.download","status":"available","attractiveness":56,"demand":7,"length":3,"created":"","expires":"","registrar":null,"sectors":"Mathematics"},{"domain":"thirtysix.download","status":"available","attractiveness":56,"demand":5,"length":10,"created":"","expires":"","registrar":null,"sectors":"Mathematics"},{"domain":"liii.download","status":"available","attractiveness":56,"demand":4,"length":4,"created":"","expires":"","registrar":null,"sectors":"Mathematics"},{"domain":"xxxii.download","status":"available","attractiveness":56,"demand":1,"length":5,"created":"","expires":"","registrar":null,"sectors":"Mathematics"},{"domain":"xliii.download","status":"available","attractiveness":56,"demand":1,"length":5,"created":"","expires":"","registrar":null,"sectors":"Mathematics"},{"domain":"xxiv.download","status":"available","attractiveness":56,"demand":5,"length":4,"created":"","expires":"","registrar":null,"sectors":"Mathematics"},{"domain":"lvi.download","status":"available","attractiveness":56,"demand":8,"length":3,"created":"","expires":"","registrar":null,"sectors":"Mathematics"},{"domain":"fiftyfive.download","status":"available","attractiveness":56,"demand":7,"length":10,"created":"","expires":"","registrar":null,"sectors":"Mathematics"},{"domain":"xli.download","status":"available","attractiveness":56,"demand":5,"length":3,"created":"","expires":"","registrar":null,"sectors":"Mathematics"},{"domain":"xxvii.download","status":"available","attractiveness":56,"demand":3,"length":5,"created":"","expires":"","registrar":null,"sectors":"Mathematics"},{"domain":"xlviii.download","status":"available","attractiveness":56,"demand":1,"length":6,"created":"","expires":"","registrar":null,"sectors":"Mathematics"},{"domain":"fiftysix.download","status":"available","attractiveness":56,"demand":4,"length":9,"created":"","expires":"","registrar":null,"sectors":"Mathematics"},{"domain":"xlvi.download","status":"available","attractiveness":56,"demand":3,"length":4,"created":"","expires":"","registrar":null,"sectors":"Mathematics"},{"domain":"thirtytwo.download","status":"available","attractiveness":56,"demand":5,"length":10,"created":"","expires":"","registrar":null,"sectors":"Mathematics"},{"domain":"xxviii.download","status":"available","attractiveness":56,"demand":1,"length":6,"created":"","expires":"","registrar":null,"sectors":"Mathematics"},{"domain":"xxxv.download","status":"available","attractiveness":56,"demand":4,"length":4,"created":"","expires":"","registrar":null,"sectors":"Mathematics"},{"domain":"xxxiv.download","status":"available","attractiveness":56,"demand":1,"length":5,"created":"","expires":"","registrar":null,"sectors":"Mathematics"},{"domain":"aone.download","status":"available","attractiveness":56,"demand":15,"length":5,"created":"","expires":"","registrar":null,"sectors":"Food and Beverage"},{"domain":"xlv.download","status":"available","attractiveness":56,"demand":6,"length":3,"created":"","expires":"","registrar":null,"sectors":"Mathematics"},{"domain":"fiftyone.download","status":"available","attractiveness":56,"demand":7,"length":9,"created":"","expires":"","registrar":null,"sectors":"Mathematics"},{"domain":"thirtyone.download","status":"available","attractiveness":56,"demand":5,"length":10,"created":"","expires":"","registrar":null,"sectors":"Mathematics"},{"domain":"halfdozen.download","status":"available","attractiveness":56,"demand":1,"length":10,"created":"","expires":"","registrar":null,"sectors":"Mathematics"},{"domain":"fortyfive.download","status":"available","attractiveness":54,"demand":4,"length":10,"created":"","expires":"","registrar":null,"sectors":"Mathematics"},{"domain":"quaternion.download","status":"available","attractiveness":54,"demand":6,"length":10,"created":"","expires":"","registrar":null,"sectors":"Mathematics"},{"domain":"twoscore.download","status":"available","attractiveness":54,"demand":2,"length":8,"created":"","expires":"","registrar":null,"sectors":"Mathematics"},{"domain":"quatern.download","status":"available","attractiveness":54,"demand":2,"length":7,"created":"","expires":"","registrar":null,"sectors":"Mathematics"},{"domain":"topnotch.download","status":"available","attractiveness":54,"demand":18,"length":8,"created":"","expires":"","registrar":null,"sectors":"Business"},{"domain":"quaternity.download","status":"available","attractiveness":54,"demand":4,"length":10,"created":"","expires":"","registrar":null,"sectors":"Mathematics"},{"domain":"threescore.download","status":"available","attractiveness":54,"demand":1,"length":10,"created":"","expires":"","registrar":null,"sectors":"Mathematics"},{"domain":"vii.download","status":"available","attractiveness":54,"demand":13,"length":3,"created":"","expires":"","registrar":null,"sectors":"Mathematics"},{"domain":"viii.download","status":"available","attractiveness":54,"demand":6,"length":4,"created":"","expires":"","registrar":null,"sectors":"Mathematics"},{"domain":"deuceace.download","status":"available","attractiveness":54,"demand":2,"length":9,"created":"","expires":"","registrar":null,"sectors":"Sports"},{"domain":"xcv.download","status":"available","attractiveness":52,"demand":7,"length":3,"created":"","expires":"","registrar":null,"sectors":"Mathematics"},{"domain":"lxxxvii.download","status":"available","attractiveness":52,"demand":1,"length":7,"created":"","expires":"","registrar":null,"sectors":"Mathematics"},{"domain":"xciii.download","status":"available","attractiveness":52,"demand":1,"length":5,"created":"","expires":"","registrar":null,"sectors":"Mathematics"},{"domain":"lxiv.download","status":"available","attractiveness":52,"demand":3,"length":4,"created":"","expires":"","registrar":null,"sectors":"Mathematics"},{"domain":"ixl.download","status":"available","attractiveness":52,"demand":9,"length":3,"created":"","expires":"","registrar":null,"sectors":"Mathematics"},{"domain":"lxxxii.download","status":"available","attractiveness":52,"demand":1,"length":6,"created":"","expires":"","registrar":null,"sectors":"Mathematics"},{"domain":"sixtysix.download","status":"available","attractiveness":52,"demand":4,"length":9,"created":"","expires":"","registrar":null,"sectors":"Mathematics"},{"domain":"lxxv.download","status":"available","attractiveness":52,"demand":1,"length":4,"created":"","expires":"","registrar":null,"sectors":"Mathematics"},{"domain":"lxxii.download","status":"available","attractiveness":52,"demand":1,"length":5,"created":"","expires":"","registrar":null,"sectors":"Mathematics"},{"domain":"lxxi.download","status":"available","attractiveness":52,"demand":1,"length":4,"created":"","expires":"","registrar":null,"sectors":"Mathematics"},{"domain":"xcviii.download","status":"available","attractiveness":52,"demand":1,"length":6,"created":"","expires":"","registrar":null,"sectors":"Mathematics"},{"domain":"lxvi.download","status":"available","attractiveness":52,"demand":3,"length":4,"created":"","expires":"","registrar":null,"sectors":"Mathematics"},{"domain":"ninetysix.download","status":"available","attractiveness":52,"demand":4,"length":10,"created":"","expires":"","registrar":null,"sectors":"Mathematics"},{"domain":"lxxxvi.download","status":"available","attractiveness":52,"demand":1,"length":6,"created":"","expires":"","registrar":null,"sectors":"Mathematics"},{"domain":"lxxiv.download","status":"available","attractiveness":52,"demand":1,"length":5,"created":"","expires":"","registrar":null,"sectors":"Mathematics"},{"domain":"lxxxi.download","status":"available","attractiveness":52,"demand":1,"length":5,"created":"","expires":"","registrar":null,"sectors":"Mathematics"},{"domain":"lxxxv.download","status":"available","attractiveness":52,"demand":1,"length":5,"created":"","expires":"","registrar":null,"sectors":"Mathematics"},{"domain":"lxvii.download","status":"available","attractiveness":52,"demand":1,"length":5,"created":"","expires":"","registrar":null,"sectors":"Mathematics"},{"domain":"xcvii.download","status":"available","attractiveness":52,"demand":1,"length":5,"created":"","expires":"","registrar":null,"sectors":"Mathematics"},{"domain":"lxiii.download","status":"available","attractiveness":52,"demand":2,"length":5,"created":"","expires":"","registrar":null,"sectors":"Mathematics"},{"domain":"lxxvii.download","status":"available","attractiveness":52,"demand":2,"length":6,"created":"","expires":"","registrar":null,"sectors":"Mathematics"},{"domain":"lxxiii.download","status":"available","attractiveness":52,"demand":1,"length":6,"created":"","expires":"","registrar":null,"sectors":"Mathematics"},{"domain":"xcvi.download","status":"available","attractiveness":52,"demand":2,"length":4,"created":"","expires":"","registrar":null,"sectors":"Mathematics"},{"domain":"ixc.download","status":"available","attractiveness":52,"demand":5,"length":3,"created":"","expires":"","registrar":null,"sectors":"Mathematics"},{"domain":"ninetyone.download","status":"available","attractiveness":52,"demand":5,"length":10,"created":"","expires":"","registrar":null,"sectors":"Mathematics"},{"domain":"ninetytwo.download","status":"available","attractiveness":52,"demand":4,"length":10,"created":"","expires":"","registrar":null,"sectors":"Mathematics"},{"domain":"eightyone.download","status":"available","attractiveness":52,"demand":3,"length":10,"created":"","expires":"","registrar":null,"sectors":"Mathematics"},{"domain":"sixtytwo.download","status":"available","attractiveness":52,"demand":3,"length":9,"created":"","expires":"","registrar":null,"sectors":"Mathematics"},{"domain":"lxi.download","status":"available","attractiveness":52,"demand":5,"length":3,"created":"","expires":"","registrar":null,"sectors":"Mathematics"},{"domain":"lxxxiii.download","status":"available","attractiveness":52,"demand":1,"length":7,"created":"","expires":"","registrar":null,"sectors":"Mathematics"},{"domain":"sixtyfive.download","status":"available","attractiveness":52,"demand":3,"length":10,"created":"","expires":"","registrar":null,"sectors":"Mathematics"},{"domain":"eightytwo.download","status":"available","attractiveness":52,"demand":4,"length":10,"created":"","expires":"","registrar":null,"sectors":"Mathematics"},{"domain":"sixtyfour.download","status":"available","attractiveness":52,"demand":3,"length":10,"created":"","expires":"","registrar":null,"sectors":"Mathematics"},{"domain":"lxviii.download","status":"available","attractiveness":52,"demand":1,"length":6,"created":"","expires":"","registrar":null,"sectors":"Mathematics"},{"domain":"lxxxiv.download","status":"available","attractiveness":52,"demand":1,"length":6,"created":"","expires":"","registrar":null,"sectors":"Mathematics"},{"domain":"xcii.download","status":"available","attractiveness":52,"demand":2,"length":4,"created":"","expires":"","registrar":null,"sectors":"Mathematics"},{"domain":"xciv.download","status":"available","attractiveness":52,"demand":2,"length":4,"created":"","expires":"","registrar":null,"sectors":"Mathematics"},{"domain":"lxxvi.download","status":"available","attractiveness":52,"demand":1,"length":5,"created":"","expires":"","registrar":null,"sectors":"Mathematics"},{"domain":"xci.download","status":"available","attractiveness":52,"demand":4,"length":3,"created":"","expires":"","registrar":null,"sectors":"Mathematics"},{"domain":"lxii.download","status":"available","attractiveness":52,"demand":1,"length":4,"created":"","expires":"","registrar":null,"sectors":"Mathematics"},{"domain":"lxv.download","status":"available","attractiveness":52,"demand":5,"length":3,"created":"","expires":"","registrar":null,"sectors":"Mathematics"},{"domain":"triplet.download","status":"available","attractiveness":50,"demand":8,"length":7,"created":"","expires":"","registrar":null,"sectors":"Science"},{"domain":"ogdoad.download","status":"available","attractiveness":50,"demand":1,"length":6,"created":"","expires":"","registrar":null,"sectors":"Mathematics"},{"domain":"lxx.download","status":"available","attractiveness":50,"demand":5,"length":3,"created":"","expires":"","registrar":null,"sectors":"Mathematics"},{"domain":"cinque.download","status":"available","attractiveness":50,"demand":7,"length":6,"created":"","expires":"","registrar":null,"sectors":"Mathematics"},{"domain":"lxxxviii.download","status":"available","attractiveness":48,"demand":1,"length":8,"created":"","expires":"","registrar":null,"sectors":"Mathematics"},{"domain":"quaternary.download","status":"available","attractiveness":46,"demand":3,"length":10,"created":"","expires":"","registrar":null,"sectors":"Mathematics"}]